halo/API.py
halo/DataStore.py
halo/Icon.py
halo/Place.py
halo/Preference.py
halo/SummaryView.py
halo/__init__.py
halo/__main__.py
halo/app.py
halo/settings.py
halo/style.css
halo/assets/bg.jpg
halo/assets/halo.svg
halo/assets/icon/wi-cloudy.svg
halo/assets/icon/wi-day-cloudy.svg
halo/assets/icon/wi-day-sunny.svg
halo/assets/icon/wi-dust.svg
halo/assets/icon/wi-fog.svg
halo/assets/icon/wi-rain-mix.svg
halo/assets/icon/wi-rain.svg
halo/assets/icon/wi-smoke.svg
halo/assets/icon/wi-snow.svg
halo/assets/icon/wi-thunderstorm.svg
home/runner/.local/share/applications/halo.desktop
home/runner/.local/share/icons/halo.svg
halo_weather-0.2.1.dist-info/LICENSE
halo_weather-0.2.1.dist-info/METADATA
halo_weather-0.2.1.dist-info/WHEEL
halo_weather-0.2.1.dist-info/entry_points.txt
halo_weather-0.2.1.dist-info/top_level.txt
halo_weather-0.2.1.dist-info/RECORD
