Metadata-Version: 2.1
Name: halo-weather
Version: 0.2.1
Summary: The weather app.
Home-page: https://github.com/cijo7/Halo
Author: Cijo Saju
Author-email: halo@cijo.mni.im
License: MIT
Platform: UNKNOWN
Requires-Dist: requests
Requires-Dist: pytz
Requires-Dist: pygobject
Requires-Dist: matplotlib
Requires-Dist: typing
